minigamesbyvedcodes/__init__.py
minigamesbyvedcodes/maths_quiz.py
minigamesbyvedcodes/rps.py
minigamesbyvedcodes/tictactoe.py
minigamesbyvedcodes/users.py
minigamesbyvedcodes-0.1.0.dist-info/METADATA
minigamesbyvedcodes-0.1.0.dist-info/WHEEL
minigamesbyvedcodes-0.1.0.dist-info/top_level.txt
minigamesbyvedcodes-0.1.0.dist-info/RECORD
