Metadata-Version: 2.4
Name: minigamesbyvedcodes
Version: 0.1.0
Summary: A simple Python games library (Tic Tac Toe, RPS, Maths Quiz)
Author: Ved Vyas (aka Ved Codes)
Author-email: vedcodes2312.dev@gmail.com
Classifier: Programming Language :: Python :: 3
Classifier: License :: OSI Approved :: MIT License
Classifier: Operating System :: OS Independent
Requires-Python: >=3.7
Dynamic: author
Dynamic: author-email
Dynamic: classifier
Dynamic: description
Dynamic: description-content-type
Dynamic: requires-python
Dynamic: summary
